djitellopy/__init__.py
djitellopy/enforce_types.py
djitellopy/swarm.py
djitellopy/tello.py
djitellopy2-2.3.dist-info/LICENSE.txt
djitellopy2-2.3.dist-info/METADATA
djitellopy2-2.3.dist-info/WHEEL
djitellopy2-2.3.dist-info/top_level.txt
djitellopy2-2.3.dist-info/RECORD
