Metadata-Version: 2.1
Name: djitellopy2
Version: 2.3
Summary: Tello drone library including support for video streaming, swarms, state packets and more
Home-page: https://github.com/damiafuentes/DJITelloPy
Author: Jakob Löw
Author-email: djitellopy2@m4gnus.de
License: MIT
Download-URL: https://github.com/damiafuentes/DJITelloPy/archive/2.1.tar.gz
Keywords: tello,dji,drone,sdk,official sdk
Platform: UNKNOWN
Classifier: Development Status :: 5 - Production/Stable
Classifier: Intended Audience :: Developers
Classifier: Topic :: Software Development :: Build Tools
Classifier: License :: OSI Approved :: MIT License
Classifier: Programming Language :: Python :: 3.6
Classifier: Programming Language :: Python :: 3.7
Classifier: Programming Language :: Python :: 3.8
Classifier: Programming Language :: Python :: 3.9
Requires-Python: >=3.6
